[
  {
    "inputs": [
      {
        "internalType": "address",
        "name": "_contract",
        "type": "address"
      }
    ],
    "name": "genCancelMsg",
    "outputs": [
      {
        "internalType": "string",
        "name": "",
        "type": "string"
      }
    ],
    "stateMutability": "view",
    "type": "function"
  },
  {
    "inputs": [
      {
        "internalType": "address",
        "name": "_contract",
        "type": "address"
      },
      {
        "internalType": "address",
        "name": "_withdrawerAddress",
        "type": "address"
      },
      {
        "internalType": "uint256[]",
        "name": "_nonces",
        "type": "uint256[]"
      }
    ],
    "name": "genRegisterMsg",
    "outputs": [
      {
        "internalType": "string",
        "name": "",
        "type": "string"
      }
    ],
    "stateMutability": "view",
    "type": "function"
  },
  {
    "inputs": [
      {
        "internalType": "address",
        "name": "_contract",
        "type": "address"
      },
      {
        "internalType": "address",
        "name": "_withdrawerAddress",
        "type": "address"
      }
    ],
    "name": "genUpdateMsg",
    "outputs": [
      {
        "internalType": "string",
        "name": "",
        "type": "string"
      }
    ],
    "stateMutability": "view",
    "type": "function"
  },
  {
    "inputs": [
      {
        "internalType": "string",
        "name": "_str",
        "type": "string"
      }
    ],
    "name": "stringToHexString",
    "outputs": [
      {
        "internalType": "string",
        "name": "",
        "type": "string"
      }
    ],
    "stateMutability": "pure",
    "type": "function"
  }
]